Metadata-Version: 1.1
Name: hdhomerun
Version: 0.1
Summary: Python bindings for libhdhomerun
Home-page: http://github.com/s-clark/python-hdhomerun
Author: Stuart Clark
Author-email: stuart.clark@Jahingo.com
License: MIT
Keywords: libhdhomerun hdhomerun
Platform: UNKNOWN
Classifier: Development Status :: 3 - Alpha
Classifier: License :: OSI Approved :: MIT License
Classifier: Programming Language :: Python :: 2.7
Classifier: Topic :: Multimedia :: Video :: Capture
Classifier: Topic :: Software Development :: Libraries
